hoopoe_iam_sdk/__init__.py
hoopoe_iam_sdk/client.py
hoopoe_iam_sdk/exceptions.py
hoopoe_iam_sdk/middleware.py
hoopoe_iam_sdk/models.py
hoopoe_iam_sdk/py.typed
hoopoe_iam_sdk/version.py
hoopoe_iam_sdk-1.0.17.dist-info/licenses/LICENSE
hoopoe_iam_sdk-1.0.17.dist-info/METADATA
hoopoe_iam_sdk-1.0.17.dist-info/WHEEL
hoopoe_iam_sdk-1.0.17.dist-info/top_level.txt
hoopoe_iam_sdk-1.0.17.dist-info/RECORD
