Metadata-Version: 2.4
Name: hoopoe-iam-sdk
Version: 1.0.17
Summary: Official Python SDK for Hoopoe IAM Service - Identity and Access Management made simple
Author-email: Eliff Technology Solutions <support@eliff.tech>
License: MIT
Project-URL: Homepage, https://github.com/eliff-tech/hoopoe-iam-sdk
Project-URL: Documentation, https://hoopoe-iam-sdk.readthedocs.io/
Project-URL: Repository, https://github.com/eliff-tech/hoopoe-iam-sdk.git
Project-URL: Issues, https://github.com/eliff-tech/hoopoe-iam-sdk/issues
Project-URL: Changelog, https://github.com/eliff-tech/hoopoe-iam-sdk/blob/main/CHANGELOG.md
Keywords: iam,identity,access,management,authentication,authorization,sdk,hoopoe
Classifier: Development Status :: 4 - Beta
Classifier: Intended Audience :: Developers
Classifier: Operating System :: OS Independent
Classifier: Programming Language :: Python :: 3
Classifier: Programming Language :: Python :: 3.8
Classifier: Programming Language :: Python :: 3.9
Classifier: Programming Language :: Python :: 3.10
Classifier: Programming Language :: Python :: 3.11
Classifier: Programming Language :: Python :: 3.12
Classifier: Topic :: Software Development :: Libraries :: Python Modules
Classifier: Topic :: Internet :: WWW/HTTP
Classifier: Topic :: Security
Classifier: Topic :: System :: Systems Administration :: Authentication/Directory
Requires-Python: >=3.8
License-File: LICENSE
Requires-Dist: httpx<0.30.0,>=0.24.0
Requires-Dist: pydantic<3.0.0,>=2.0.0
Requires-Dist: python-dotenv<2.0.0,>=1.0.0
Requires-Dist: typing-extensions>=4.0.0; python_version < "3.10"
Requires-Dist: pydantic[email]
Requires-Dist: email-validator
Requires-Dist: pydantic-settings
Provides-Extra: fastapi
Requires-Dist: fastapi>=0.100.0; extra == "fastapi"
Provides-Extra: dev
Requires-Dist: pytest>=7.0.0; extra == "dev"
Requires-Dist: pytest-asyncio>=0.21.0; extra == "dev"
Requires-Dist: pytest-cov>=4.0.0; extra == "dev"
Requires-Dist: black>=23.0.0; extra == "dev"
Requires-Dist: isort>=5.12.0; extra == "dev"
Requires-Dist: flake8>=6.0.0; extra == "dev"
Requires-Dist: mypy>=1.0.0; extra == "dev"
Requires-Dist: pre-commit>=3.0.0; extra == "dev"
Requires-Dist: twine>=4.0.0; extra == "dev"
Requires-Dist: build>=0.10.0; extra == "dev"
Provides-Extra: docs
Requires-Dist: mkdocs>=1.4.0; extra == "docs"
Requires-Dist: mkdocs-material>=8.0.0; extra == "docs"
Requires-Dist: mkdocstrings[python]>=0.20.0; extra == "docs"
Dynamic: license-file
